mypackage/__init__.py
mypackage/aoc2018/__init__.py
mypackage/aoc2018/day1.py
mypackage/aoc2018/day2.py
advent_of_code_sample-0.1.dist-info/METADATA
advent_of_code_sample-0.1.dist-info/WHEEL
advent_of_code_sample-0.1.dist-info/entry_points.txt
advent_of_code_sample-0.1.dist-info/top_level.txt
advent_of_code_sample-0.1.dist-info/RECORD
