Metadata-Version: 2.1
Name: advent-of-code-sample
Version: 0.1
Summary: myusername's solutions for https://adventofcode.com/
Home-page: https://github.com/myusername/advent-of-code-myusername
Author: My Username
Author-email: myusername@example.com
License: UNKNOWN
Platform: UNKNOWN
Classifier: Programming Language :: Python :: 3
Classifier: Topic :: Games/Entertainment :: Puzzle Games
Requires-Dist: advent-of-code-data (>=0.8.0)
